Metadata-Version: 2.2
Name: DARTassembler
Version: 1.0.4
Summary: Simple to use package for building 3D structures of novel transition metal complexes from a large database of ligands extracted from the Cambridge Structural Database.
Home-page: https://github.com/CCEMGroupTCD/DARTassembler
Author: Timo Sommer, Cian Clarke, Felix Kleuker
Requires-Python: >=3.9
License-File: LICENSE
Requires-Dist: ase
Requires-Dist: jsonlines
Requires-Dist: networkx
Requires-Dist: numpy
Requires-Dist: openbabel-wheel
Requires-Dist: pandas
Requires-Dist: pyyaml
Requires-Dist: rdkit
Requires-Dist: scipy
Requires-Dist: scikit-learn
Requires-Dist: stk
Requires-Dist: sympy
Requires-Dist: tqdm
Requires-Dist: pysmiles
Dynamic: author
Dynamic: description
Dynamic: description-content-type
Dynamic: home-page
Dynamic: requires-dist
Dynamic: requires-python
Dynamic: summary
